asking_more_questions/__init__.py
asking_more_questions/ask.py
asking_more_questions/client.py
asking_more_questions/connections.py
asking_more_questions/models.py
asking_more_questions-0.1.3.dist-info/entry_points.txt
asking_more_questions-0.1.3.dist-info/WHEEL
asking_more_questions-0.1.3.dist-info/METADATA
asking_more_questions-0.1.3.dist-info/RECORD
